portfolio_tools/__init__.py
portfolio_tools/portfolio.py
portfolio_tools-0.1.dist-info/METADATA
portfolio_tools-0.1.dist-info/RECORD
portfolio_tools-0.1.dist-info/WHEEL
portfolio_tools-0.1.dist-info/top_level.txt
