Metadata-Version: 2.1
Name: portfolio-tools
Version: 0.1
Summary: Tools for working with portfolios of securities
Home-page: UNKNOWN
Author: Pete Massaro
Author-email: peter.j.massaro@gmail.com
License: MIT
Platform: UNKNOWN
